LICENSE
MANIFEST.in
README.md
setup.py
Flask_SOEditor.egg-info/PKG-INFO
Flask_SOEditor.egg-info/SOURCES.txt
Flask_SOEditor.egg-info/dependency_links.txt
Flask_SOEditor.egg-info/not-zip-safe
Flask_SOEditor.egg-info/requires.txt
Flask_SOEditor.egg-info/top_level.txt
flask_soeditor/__init__.py