Metadata-Version: 1.1
Name: Flask-SOEditor
Version: 0.1.2a0
Summary: A Stack Overflow editor extension for Flask.
Home-page: https://github.com/zeleven/flask-soeditor
Author: zeleven
Author-email: chengsmo@outlook.com
License: MIT
Platform: any
Classifier: Environment :: Web Environment
Classifier: Intended Audience :: Developers
Classifier: License :: OSI Approved :: MIT License
Classifier: Operating System :: OS Independent
Classifier: Programming Language :: Python
Classifier: Programming Language :: Python :: 2
Classifier: Programming Language :: Python :: 2.7
Classifier: Programming Language :: Python :: 3
Classifier: Programming Language :: Python :: 3.4
Classifier: Topic :: Internet :: WWW/HTTP :: Dynamic Content
Classifier: Topic :: Software Development :: Libraries :: Python Modules
